{
  "app_path": "/Users/i/Projects",
  "app_name": "my_app_name",
  "angular_js_material": true,
  "font_awesome": true,
  "turbolinks": false, // false - remove turbolinks; true - leave
  "gems": ["gem 'devise'", "gem 'activeadmin'", "gem 'cancancan'"],
  "devise": true,
  "controllers": {
    "flow": ["index", "about"],
    "categories": ["index", "show"]
  },
  "scaffolds": {
    "product": {
      "name": "string",
      "description": "text"
    }
  },
  "models": {
    "category": {
      "name": "string"
    },
    "subcategory": {
      "name": "string",
      "category": "belongs_to"
    }
  }
}
